libexcs/__init__.py
libexcs/_utils.py
libexcs/root.py
libexcs-0.0.2.dist-info/LICENSE
libexcs-0.0.2.dist-info/METADATA
libexcs-0.0.2.dist-info/WHEEL
libexcs-0.0.2.dist-info/top_level.txt
libexcs-0.0.2.dist-info/RECORD
