Metadata-Version: 2.1
Name: libexcs
Version: 0.0.2
Summary: An exceptional library
Author-email: Dima Burmistrov <pyctrl.dev@gmail.com>
Project-URL: Homepage, https://gitlab.com/pyctrl/libexcs
Project-URL: Bug Tracker, https://gitlab.com/pyctrl/libexcs/-/issues
Keywords: exception,exceptions
Classifier: Programming Language :: Python :: 3
Classifier: License :: OSI Approved :: MIT License
Classifier: Operating System :: OS Independent
Requires-Python: >=3.9
License-File: LICENSE
